abnf_to_regexp/__init__.py
abnf_to_regexp/__main__.py
abnf_to_regexp/abnf_transformation.py
abnf_to_regexp/base.py
abnf_to_regexp/compression.py
abnf_to_regexp/main.py
abnf_to_regexp/nested_python.py
abnf_to_regexp/py.typed
abnf_to_regexp/representation.py
abnf_to_regexp/single_regexp.py
abnf_to_regexp-1.2.0.dist-info/licenses/AUTHORS
abnf_to_regexp-1.2.0.dist-info/licenses/LICENSE
abnf_to_regexp-1.2.0.dist-info/METADATA
abnf_to_regexp-1.2.0.dist-info/WHEEL
abnf_to_regexp-1.2.0.dist-info/entry_points.txt
abnf_to_regexp-1.2.0.dist-info/top_level.txt
abnf_to_regexp-1.2.0.dist-info/RECORD
