Metadata-Version: 2.4
Name: abnf-to-regexp
Version: 1.2.0
Summary: Convert ABNF grammars to Python regular expressions.
Author-email: Marko Ristin <marko@ristin.ch>
License: MIT
Project-URL: Homepage, https://github.com/aas-core-works/abnf-to-regexp
Keywords: abnf,backus-naur,convert,regular,expressions
Classifier: Development Status :: 5 - Production/Stable
Classifier: License :: OSI Approved :: MIT License
Classifier: Programming Language :: Python :: 3.9
Classifier: Programming Language :: Python :: 3.10
Classifier: Programming Language :: Python :: 3.11
Classifier: Programming Language :: Python :: 3.12
Classifier: Programming Language :: Python :: 3.13
Requires-Python: >=3.9
License-File: LICENSE
License-File: AUTHORS
Requires-Dist: icontract<3,>=2.5.1
Requires-Dist: regex==2021.4.4
Requires-Dist: abnf<2.3.0,>=2.0
Requires-Dist: sortedcontainers<3,>=2
Provides-Extra: dev
Requires-Dist: black==24.3.0; extra == "dev"
Requires-Dist: mypy==1.18.2; extra == "dev"
Requires-Dist: pylint==3.3.9; (python_version >= "3.9" and python_version < "3.12") and extra == "dev"
Requires-Dist: pylint==4.0.2; python_version >= "3.12" and extra == "dev"
Requires-Dist: pydocstyle<3,>=2.1.1; extra == "dev"
Requires-Dist: coverage<8,>=7; extra == "dev"
Requires-Dist: docutils<1,>=0.14; extra == "dev"
Requires-Dist: pygments<3,>=2; extra == "dev"
Dynamic: license-file
